anansi/__init__.py
anansi/escape_char.py
anansi/font/__init__.py
anansi/font/esc.py
anansi/font/colors/__init__.py
anansi/font/colors/_color_id.py
anansi/font/colors/background/__init__.py
anansi/font/colors/background/_background.py
anansi/font/colors/foreground/__init__.py
anansi/font/colors/foreground/_foreground.py
anansi/font/effects/__init__.py
anansi/font/effects/_effects.py
anansi/font/ideograms/__init__.py
anansi/font/ideograms/_ideograms.py
py_anansi-0.0.0.0.dist-info/METADATA
py_anansi-0.0.0.0.dist-info/WHEEL
py_anansi-0.0.0.0.dist-info/RECORD
