Metadata-Version: 2.3
Name: py-anansi
Version: 0.0.0.0
Summary: `anansi` (`ANother ANSI`) is yet antoher python library for ANSI escape characters.
Project-URL: Repository, https://github.com/solidtony/py-anansi.git
Author-email: Anthony Garcia <anthonygarcia918@hotmail.com>
Keywords: ansi,color,escape,terminal
Classifier: License :: OSI Approved :: MIT License
Classifier: Operating System :: OS Independent
Classifier: Programming Language :: Python :: 3
Requires-Python: >=3.7
